htmllistparse/__init__.py
htmllistparse/htmllistparse.py
htmllistparse/rehttpfs.py
htmllistparse-0.6.1.dist-info/LICENSE
htmllistparse-0.6.1.dist-info/METADATA
htmllistparse-0.6.1.dist-info/WHEEL
htmllistparse-0.6.1.dist-info/entry_points.txt
htmllistparse-0.6.1.dist-info/top_level.txt
htmllistparse-0.6.1.dist-info/RECORD
