Metadata-Version: 2.1
Name: htmllistparse
Version: 0.6.1
Summary: Python parser for Apache/nginx-style HTML directory listing.
Home-page: https://github.com/gumblex/htmllisting-parser
Author: Dingyuan Wang
Author-email: gumblex@aosc.io
License: MIT
Keywords: apache nginx listing fuse
Platform: any
Classifier: Development Status :: 4 - Beta
Classifier: Intended Audience :: Developers
Classifier: License :: OSI Approved :: MIT License
Classifier: Topic :: Internet :: WWW/HTTP
Classifier: Programming Language :: Python :: 3
Classifier: Programming Language :: Python :: 3 :: Only
License-File: LICENSE
Requires-Dist: beautifulsoup4
Requires-Dist: fusepy
Requires-Dist: html5lib
Requires-Dist: requests
